localize/__init__.py
localize/commands.py
localize/localize.py
tests/__init__.py
tests/bootstrap.py
tests/unit/__init__.py
tests/unit/test_config.py
tests/unit/test_get_url.py
tests/unit/test_lang_format.py
tests/unit/test_pull.py
tests/unit/test_push.py
tests/unit/test_utils.py
localize-1.2.2.dist-info/LICENSE.txt
localize-1.2.2.dist-info/METADATA
localize-1.2.2.dist-info/WHEEL
localize-1.2.2.dist-info/entry_points.txt
localize-1.2.2.dist-info/top_level.txt
localize-1.2.2.dist-info/RECORD
