Metadata-Version: 2.1
Name: localize
Version: 1.2.2
Summary: Command line utility for Localize.
Home-page: https://help.localizejs.com/docs/localize-cli
Author: Localize
Author-email: support@localizejs.com
License: MIT
Platform: Posix; MacOS X; Windows
Classifier: Development Status :: 5 - Production/Stable
Classifier: Intended Audience :: Developers
Classifier: License :: OSI Approved :: MIT License
Classifier: Operating System :: OS Independent
Classifier: Topic :: Internet
Classifier: Programming Language :: Python :: 3.9
License-File: LICENSE.txt
Requires-Dist: requests (==2.31.0)
Requires-Dist: colorama (==0.4.4)
Requires-Dist: pyyaml (==5.4.1)
